<beans xmlns="http://www.springframework.org/schema/beans"
       xmlns:xsi="http://www.w3.org/2001/XMLSchema-instance"
       xsi:schemaLocation="http://www.springframework.org/schema/beans
		http://www.springframework.org/schema/beans/spring-beans.xsd" default-lazy-init="true">

    <import resource="classpath:/pulsar-beans/components-context.xml" />

    <bean id="serverInstanceService" class="ai.platon.pulsar.rest.service.ServerInstanceService">
        <constructor-arg ref="ormliteDaoFactory"/>
        <constructor-arg name="autoTruncate" value="true"/>
    </bean>

    <bean id="browserInstanceService" class="ai.platon.pulsar.rest.service.BrowserInstanceService">
        <constructor-arg ref="ormliteDaoFactory"/>
        <constructor-arg name="autoTruncate" value="true"/>
    </bean>

</beans>
